<annotation>
  <folder>augmentation/images</folder>
  <filename>00047_3.jpg</filename>
  <path>augmentation/images\00047_3.jpg</path>
  <source>
    <database>Unknown</database>
  </source>
  <size>
    <width>1505</width>
    <height>500</height>
    <depth>3</depth>
  </size>
  <segmented>0</segmented>
  <object>
    <name>class6</name>
    <pose>Unspecified</pose>
    <truncated>0</truncated>
    <difficult>0</difficult>
    <bndbox>
      <xmin>110</xmin>
      <ymin>80</ymin>
      <xmax>189</xmax>
      <ymax>147</ymax>
    </bndbox>
  </object>
</annotation>
