<annotation><folder>images</folder><filename>00056.jpg</filename><size><width>1904</width><height>608</height><depth>3</depth></size><object><name>class6</name><pose>Unspecified</pose><truncated>0</truncated><difficult>0</difficult><bndbox><xmin>972</xmin><ymin>323</ymin><xmax>1060</xmax><ymax>413</ymax></bndbox></object><object><name>class3</name><pose>Unspecified</pose><truncated>0</truncated><difficult>0</difficult><bndbox><xmin>818</xmin><ymin>383</ymin><xmax>869</xmax><ymax>418</ymax></bndbox></object><object><name>class2</name><pose>Unspecified</pose><truncated>0</truncated><difficult>0</difficult><bndbox><xmin>1681</xmin><ymin>131</ymin><xmax>1698</xmax><ymax>148</ymax></bndbox></object></annotation>