<annotation><folder>images</folder><filename>00245.jpg</filename><size><width>1904</width><height>608</height><depth>3</depth></size><object><name>class3</name><pose>Unspecified</pose><truncated>0</truncated><difficult>0</difficult><bndbox><xmin>480</xmin><ymin>358</ymin><xmax>578</xmax><ymax>392</ymax></bndbox></object><object><name>class2</name><pose>Unspecified</pose><truncated>0</truncated><difficult>0</difficult><bndbox><xmin>642</xmin><ymin>396</ymin><xmax>697</xmax><ymax>416</ymax></bndbox></object><object><name>class2</name><pose>Unspecified</pose><truncated>0</truncated><difficult>0</difficult><bndbox><xmin>952</xmin><ymin>499</ymin><xmax>1004</xmax><ymax>525</ymax></bndbox></object><object><name>class5</name><pose>Unspecified</pose><truncated>0</truncated><difficult>0</difficult><bndbox><xmin>935</xmin><ymin>312</ymin><xmax>980</xmax><ymax>331</ymax></bndbox></object></annotation>