<annotation>
  <folder>augmentation/images</folder>
  <filename>00404_5.jpg</filename>
  <path>augmentation/images\00404_5.jpg</path>
  <source>
    <database>Unknown</database>
  </source>
  <size>
    <width>595</width>
    <height>447</height>
    <depth>3</depth>
  </size>
  <segmented>0</segmented>
  <object>
    <name>class4</name>
    <pose>Unspecified</pose>
    <truncated>0</truncated>
    <difficult>0</difficult>
    <bndbox>
      <xmin>-576</xmin>
      <ymin>218</ymin>
      <xmax>-483</xmax>
      <ymax>258</ymax>
    </bndbox>
  </object>
  <object>
    <name>class2</name>
    <pose>Unspecified</pose>
    <truncated>0</truncated>
    <difficult>0</difficult>
    <bndbox>
      <xmin>-321</xmin>
      <ymin>120</ymin>
      <xmax>-285</xmax>
      <ymax>134</ymax>
    </bndbox>
  </object>
</annotation>
