<annotation>
  <folder>augmentation/images</folder>
  <filename>00503_2.jpg</filename>
  <path>augmentation/images\00503_2.jpg</path>
  <source>
    <database>Unknown</database>
  </source>
  <size>
    <width>580</width>
    <height>438</height>
    <depth>3</depth>
  </size>
  <segmented>0</segmented>
  <object>
    <name>class5</name>
    <pose>Unspecified</pose>
    <truncated>0</truncated>
    <difficult>0</difficult>
    <bndbox>
      <xmin>191</xmin>
      <ymin>228</ymin>
      <xmax>220</xmax>
      <ymax>256</ymax>
    </bndbox>
  </object>
  <object>
    <name>class5</name>
    <pose>Unspecified</pose>
    <truncated>0</truncated>
    <difficult>0</difficult>
    <bndbox>
      <xmin>423</xmin>
      <ymin>154</ymin>
      <xmax>457</xmax>
      <ymax>187</ymax>
    </bndbox>
  </object>
</annotation>
