<annotation>
  <folder>augmentation/images</folder>
  <filename>00591_2.jpg</filename>
  <path>augmentation/images\00591_2.jpg</path>
  <source>
    <database>Unknown</database>
  </source>
  <size>
    <width>800</width>
    <height>600</height>
    <depth>3</depth>
  </size>
  <segmented>0</segmented>
  <object>
    <name>class5</name>
    <pose>Unspecified</pose>
    <truncated>0</truncated>
    <difficult>0</difficult>
    <bndbox>
      <xmin>469</xmin>
      <ymin>227</ymin>
      <xmax>506</xmax>
      <ymax>265</ymax>
    </bndbox>
  </object>
  <object>
    <name>class2</name>
    <pose>Unspecified</pose>
    <truncated>0</truncated>
    <difficult>0</difficult>
    <bndbox>
      <xmin>565</xmin>
      <ymin>419</ymin>
      <xmax>592</xmax>
      <ymax>445</ymax>
    </bndbox>
  </object>
</annotation>
