<annotation>
  <folder>augmentation/images</folder>
  <filename>00626_2.jpg</filename>
  <path>augmentation/images\00626_2.jpg</path>
  <source>
    <database>Unknown</database>
  </source>
  <size>
    <width>960</width>
    <height>600</height>
    <depth>3</depth>
  </size>
  <segmented>0</segmented>
  <object>
    <name>class5</name>
    <pose>Unspecified</pose>
    <truncated>0</truncated>
    <difficult>0</difficult>
    <bndbox>
      <xmin>1487</xmin>
      <ymin>334</ymin>
      <xmax>1582</xmax>
      <ymax>379</ymax>
    </bndbox>
  </object>
  <object>
    <name>class4</name>
    <pose>Unspecified</pose>
    <truncated>0</truncated>
    <difficult>0</difficult>
    <bndbox>
      <xmin>803</xmin>
      <ymin>454</ymin>
      <xmax>922</xmax>
      <ymax>505</ymax>
    </bndbox>
  </object>
  <object>
    <name>class4</name>
    <pose>Unspecified</pose>
    <truncated>0</truncated>
    <difficult>0</difficult>
    <bndbox>
      <xmin>628</xmin>
      <ymin>449</ymin>
      <xmax>751</xmax>
      <ymax>511</ymax>
    </bndbox>
  </object>
  <object>
    <name>class2</name>
    <pose>Unspecified</pose>
    <truncated>0</truncated>
    <difficult>0</difficult>
    <bndbox>
      <xmin>188</xmin>
      <ymin>139</ymin>
      <xmax>224</xmax>
      <ymax>158</ymax>
    </bndbox>
  </object>
  <object>
    <name>class2</name>
    <pose>Unspecified</pose>
    <truncated>0</truncated>
    <difficult>0</difficult>
    <bndbox>
      <xmin>174</xmin>
      <ymin>131</ymin>
      <xmax>206</xmax>
      <ymax>146</ymax>
    </bndbox>
  </object>
</annotation>
